dlotter/__init__.py
dlotter/__main__.py
dlotter/arguments.py
dlotter/comeps.py
dlotter/meteogram.py
dlotter/plot.py
dlotter/prepare.py
dlotter/read.py
dlotter/icons/0.png
dlotter/icons/1.png
dlotter/icons/1000.png
dlotter/icons/1001.png
dlotter/icons/1002.png
dlotter/icons/1003.png
dlotter/icons/101.png
dlotter/icons/102.png
dlotter/icons/1101.png
dlotter/icons/1102.png
dlotter/icons/111.png
dlotter/icons/1111.png
dlotter/icons/1112.png
dlotter/icons/112.png
dlotter/icons/1201.png
dlotter/icons/1202.png
dlotter/icons/1211.png
dlotter/icons/1212.png
dlotter/icons/1301.png
dlotter/icons/1302.png
dlotter/icons/1311.png
dlotter/icons/1312.png
dlotter/icons/2.png
dlotter/icons/201.png
dlotter/icons/202.png
dlotter/icons/211.png
dlotter/icons/212.png
dlotter/icons/3.png
dlotter/icons/301.png
dlotter/icons/302.png
dlotter/icons/311.png
dlotter/icons/312.png
dlotter-0.1.0.dist-info/LICENSE
dlotter-0.1.0.dist-info/METADATA
dlotter-0.1.0.dist-info/WHEEL
dlotter-0.1.0.dist-info/top_level.txt
dlotter-0.1.0.dist-info/RECORD
