Metadata-Version: 2.1
Name: dlotter
Version: 0.1.0
Summary: Quick and dirty static plots of NWP output
Home-page: https://dmidk.github.io/dlotter/
Author: Kasper Hintz
Author-email: kah@dmi.dk
License: UNKNOWN
Platform: UNKNOWN
Classifier: Programming Language :: Python :: 3
Classifier: License :: OSI Approved :: MIT License
Classifier: Operating System :: OS Independent
License-File: LICENSE
Requires-Dist: wheel
Requires-Dist: dmit
Requires-Dist: xarray
Requires-Dist: numpy
Requires-Dist: cartopy
Requires-Dist: eccodes
Requires-Dist: pygrib
Requires-Dist: scipy
